Metadata-Version: 2.1
Name: matrix-transpose
Version: 1.3
Summary: matrix transpose
Home-page: https://github.com/noushadkhan01/matrix_transpose
Author: Noushad Khan
Author-email: noushadkhan1994@gmail.com
License: UNKNOWN
Platform: UNKNOWN
Classifier: Programming Language :: Python :: 3
Classifier: License :: OSI Approved :: MIT License
Classifier: Operating System :: OS Independent
Requires-Python: >=3.6
